aws_obp/__init__.py
aws_obp/auto_scaling.py
aws_obp/ec2.py
aws_obp/lambda_fn.py
aws_obp/lb.py
aws_obp/rds.py
aws_obp/s3.py
aws_obp/utils.py
aws_obp-0.0.1.dist-info/METADATA
aws_obp-0.0.1.dist-info/WHEEL
aws_obp-0.0.1.dist-info/top_level.txt
aws_obp-0.0.1.dist-info/RECORD
